setup.py
melange_downloader/__init__.py
melange_downloader/melange.py
melange_downloader.egg-info/PKG-INFO
melange_downloader.egg-info/SOURCES.txt
melange_downloader.egg-info/dependency_links.txt
melange_downloader.egg-info/not-zip-safe
melange_downloader.egg-info/requires.txt
melange_downloader.egg-info/top_level.txt