Metadata-Version: 1.0
Name: melange-downloader
Version: 0.4
Summary: Download testimonials in a sorted way from BITS Melange website.
Home-page: http://github.com/bhavul/testimonials-downloader
Author: Bhavul Gauri
Author-email: bhavul93@gmail.com
License: MIT
Platform: UNKNOWN
